{
    "Plugins": [
        {
            "Info": {
                "Types": {
                    "UsdMediaSpatialAudio": {
                        "alias": {
                            "UsdSchemaBase": "SpatialAudio"
                        },
                        "autoGenerated": true,
                        "bases": [
                            "UsdGeomXformable"
                        ],
                        "schemaKind": "concreteTyped"
                    }
                }
            },
            "LibraryPath": "../../../usd_core.libs/libusdMedia-4ee9938e.so",
            "Name": "usdMedia",
            "ResourcePath": "resources",
            "Root": "..",
            "Type": "library"
        }
    ]
}